sisyphe/__init__.py
sisyphe/display.py
sisyphe/initial.py
sisyphe/kernels.py
sisyphe/models.py
sisyphe/particles.py
sisyphe/sampling.py
sisyphe/toolbox.py
sisyphe/test/__init__.py
sisyphe/test/quick_test.py
sisyphe/test/test_script.py
sisyphe-0.1.6.dist-info/METADATA
sisyphe-0.1.6.dist-info/WHEEL
sisyphe-0.1.6.dist-info/top_level.txt
sisyphe-0.1.6.dist-info/RECORD
